{
    "version": 6,
    "cmakeMinimumRequired": {
        "major": 3,
        "minor": 16,
        "patch": 0
    },
    "configurePresets": [
        {
            "name": "windows-base",
            "hidden": true,
            "generator": "Ninja",
            "binaryDir": "${sourceDir}/build/${presetName}",
            "installDir": "${sourceDir}/install/${presetName}",
            "toolchainFile": "$env{VCPKG_INSTALLED}/scripts/buildsystems/vcpkg.cmake",
            "environment": {
                "VCPKG_DEFAULT_TRIPLET": "x64-windows-static",
                "VCPKG_DEFAULT_HOST_TRIPLET": "x64-windows-static"
            },
            "cacheVariables": {
                "VCPKG_TARGET_TRIPLET": "x64-windows-static",
                "CMAKE_EXPORT_COMPILE_COMMANDS": "ON"
            }
        },
        {
            "name": "windows-msvc-debug",
            "displayName": "Windows MSVC Debug",
            "inherits": "windows-base",
            "condition": {
                "type": "equals",
                "lhs": "${hostSystemName}",
                "rhs": "Windows"
            },
            "architecture": {
                "value": "x64",
                "strategy": "external"
            },
            "cacheVariables": {
                "CMAKE_BUILD_TYPE": "Debug",
                "CMAKE_C_COMPILER": "cl",
                "CMAKE_CXX_COMPILER": "cl"
            }
        },
        {
            "name": "windows-msvc-release",
            "displayName": "Windows MSVC Release",
            "inherits": "windows-base",
            "condition": {
                "type": "equals",
                "lhs": "${hostSystemName}",
                "rhs": "Windows"
            },
            "architecture": {
                "value": "x64",
                "strategy": "external"
            },
            "cacheVariables": {
                "CMAKE_BUILD_TYPE": "Release",
                "CMAKE_C_COMPILER": "cl",
                "CMAKE_CXX_COMPILER": "cl"
            }
        }
    ],
    "buildPresets": [
        {
            "name": "debug",
            "displayName": "Build Debug",
            "configurePreset": "windows-msvc-debug",
            "configuration": "Debug"
        },
        {
            "name": "release",
            "displayName": "Build Release",
            "configurePreset": "windows-msvc-release",
            "configuration": "Release"
        },
        {
            "name": "hot-reload",
            "displayName": "Build game.dll only (hot-reload)",
            "configurePreset": "windows-msvc-debug",
            "configuration": "Debug",
            "targets": [
                "game_dll"
            ]
        }
    ]
}
